teradatamlspk/LICENSE-3RD-PARTY.pdf
teradatamlspk/LICENSE.pdf
teradatamlspk/README.md
teradatamlspk/__init__.py
teradatamlspk/_version.py
teradatamlspk/conf.py
teradatamlspk/context.py
teradatamlspk/exceptions.py
teradatamlspk/storagelevel.py
teradatamlspk/common/__init__.py
teradatamlspk/common/constants.py
teradatamlspk/converter/__init__.py
teradatamlspk/converter/constants.py
teradatamlspk/converter/dynamic_user_notes.json
teradatamlspk/converter/object_types.py
teradatamlspk/converter/read_write_interactive.py
teradatamlspk/converter/user_notes.json
teradatamlspk/converter/utils.py
teradatamlspk/converter/examples/MaxAbsScaler.txt
teradatamlspk/converter/examples/MinMaxScaler.txt
teradatamlspk/converter/examples/OneHotEncoder.txt
teradatamlspk/converter/examples/Pipeline.txt
teradatamlspk/converter/examples/RegexTokenizer.txt
teradatamlspk/converter/examples/StandardScaler.txt
teradatamlspk/converter/examples/Tokenizer.txt
teradatamlspk/converter/examples/UnivariateFeatureSelector.txt
teradatamlspk/converter/examples/VarianceThresholdSelector.txt
teradatamlspk/converter/examples/array.txt
teradatamlspk/converter/examples/array_agg.txt
teradatamlspk/converter/examples/array_append.txt
teradatamlspk/converter/examples/array_compact.txt
teradatamlspk/converter/examples/array_contains.txt
teradatamlspk/converter/examples/array_distinct.txt
teradatamlspk/converter/examples/array_except.txt
teradatamlspk/converter/examples/array_insert.txt
teradatamlspk/converter/examples/array_intersect.txt
teradatamlspk/converter/examples/array_join.txt
teradatamlspk/converter/examples/array_max.txt
teradatamlspk/converter/examples/array_min.txt
teradatamlspk/converter/examples/array_position.txt
teradatamlspk/converter/examples/array_prepend.txt
teradatamlspk/converter/examples/array_remove.txt
teradatamlspk/converter/examples/array_repeat.txt
teradatamlspk/converter/examples/array_sort.txt
teradatamlspk/converter/examples/array_union.txt
teradatamlspk-20.0.0.4.dist-info/METADATA
teradatamlspk-20.0.0.4.dist-info/WHEEL
teradatamlspk-20.0.0.4.dist-info/top_level.txt
teradatamlspk-20.0.0.4.dist-info/zip-safe
teradatamlspk-20.0.0.4.dist-info/RECORD
