Metadata-Version: 2.1
Name: teradatamlspk
Version: 20.0.0.4
Summary: Python package for running Spark workloads on Teradata Vantage
Home-page: http://www.teradata.com/
Author: Teradata Corporation
License: Teradata License Agreement
Keywords: Teradata
Platform: MacOS X, Windows, Linux
Classifier: Programming Language :: Python :: 3 :: Only
Classifier: Programming Language :: Python :: 3.7
Classifier: Operating System :: Microsoft :: Windows
Classifier: Operating System :: MacOS :: MacOS X
Classifier: Operating System :: POSIX :: Linux
Classifier: Topic :: Database :: Front-Ends
Classifier: License :: Other/Proprietary License
Requires-Python: >=3.9
Requires-Dist: teradataml (>=20.0.0.9)
Requires-Dist: PrettyTable
Requires-Dist: nbformat
Requires-Dist: pytz
Requires-Dist: pygments (==2.19.0)
Requires-Dist: jinja2
Requires-Dist: mistune
